{"metadata":{"prefix":"zab","shardId":"7a-61-62","count":68},"fields":["id","sku","brand","brandSlug","name","nameOriginal","category","price","sourcePrice","oldPrice","oldSourcePrice","currency","visual","icon","stock","url","image","availability","priceUpdatedAt","lastFetchedAt"],"products":[["amazone-ke0101","KE0101","AMAZONE","amazone","Ząb brony aktywnej, przedni ZAMIENNIK","Ząb brony aktywnej, przedni ZAMIENNIK","tractor",16.68,13.9,0,0,"EUR","blue","package","Цена обновлена","https://bartsparts.com/products/amazone-ke0101/","https://store-77uyis7lbs.mybigcommerce.com/content/images/brands/amazone.png","in_stock","2026-05-14T22:26:25.011Z","2026-05-14T22:26:25.011Z"],["amazone-ke0106","KE0106","AMAZONE","amazone","Ząb brony aktywnej, prawy KE0106 ZAMIENNIK","Ząb brony aktywnej, prawy KE0106 ZAMIENNIK","tractor",14.24,11.87,0,0,"EUR","blue","package","Цена обновлена","https://bartsparts.com/products/amazone-ke0106/","https://store-77uyis7lbs.mybigcommerce.com/content/images/brands/amazone.png","in_stock","2026-05-14T22:26:25.011Z","2026-05-14T22:26:25.011Z"],["amazone-ke0107","KE0107","AMAZONE","amazone","Ząb brony aktywnej, lewy KE0107 ZAMIENNIK","Ząb brony aktywnej, lewy KE0107 ZAMIENNIK","tractor",17.99,14.99,0,0,"EUR","blue","package","Цена обновлена","https://bartsparts.com/products/amazone-ke0107/","https://store-77uyis7lbs.mybigcommerce.com/content/images/brands/amazone.png","in_stock","2026-05-14T22:26:25.011Z","2026-05-14T22:26:25.011Z"],["amazone-ke0108","KE0108","AMAZONE","amazone","Ząb brony aktywnej, prawy KE0108 ZAMIENNIK","Ząb brony aktywnej, prawy KE0108 ZAMIENNIK","tractor",17.99,14.99,0,0,"EUR","blue","package","Цена обновлена","https://bartsparts.com/products/amazone-ke0108/","https://store-77uyis7lbs.mybigcommerce.com/content/images/brands/amazone.png","in_stock","2026-05-14T22:26:25.011Z","2026-05-14T22:26:25.011Z"],["amazone-ke1001","KE1001","AMAZONE","amazone","Ząb brony aktywnej, lewy. Niemeyer ZAMIENNIK","Ząb brony aktywnej, lewy. Niemeyer ZAMIENNIK","tractor",16.36,13.63,0,0,"EUR","blue","package","Цена обновлена","https://bartsparts.com/products/amazone-ke1001/","https://store-77uyis7lbs.mybigcommerce.com/content/images/brands/amazone.png","in_stock","2026-05-14T22:26:25.011Z","2026-05-14T22:26:25.011Z"],["amazone-ke1301","KE1301","AMAZONE","amazone","Ząb brony aktywnej, lewy KE1301 ZAMIENNIK","Ząb brony aktywnej, lewy KE1301 ZAMIENNIK","tractor",14.54,12.12,0,0,"EUR","blue","package","Цена обновлена","https://bartsparts.com/products/amazone-ke1301/","https://store-77uyis7lbs.mybigcommerce.com/content/images/brands/amazone.png","in_stock","2026-05-14T22:26:25.011Z","2026-05-14T22:26:25.011Z"],["amazone-ke1302","KE1302","AMAZONE","amazone","Ząb brony aktywnej, prawy KE1302 ZAMIENNIK","Ząb brony aktywnej, prawy KE1302 ZAMIENNIK","tractor",9.19,7.66,0,0,"EUR","blue","package","Цена обновлена","https://bartsparts.com/products/amazone-ke1302/","https://store-77uyis7lbs.mybigcommerce.com/content/images/brands/amazone.png","in_stock","2026-05-14T22:26:25.011Z","2026-05-14T22:26:25.011Z"],["amazone-ke1304","KE1304","AMAZONE","amazone","Ząb brony aktywnej, prawy KE1304 ZAMIENNIK","Ząb brony aktywnej, prawy KE1304 ZAMIENNIK","tractor",18.82,15.68,0,0,"EUR","blue","package","Цена обновлена","https://bartsparts.com/products/amazone-ke1304/","https://store-77uyis7lbs.mybigcommerce.com/content/images/brands/amazone.png","in_stock","2026-05-14T22:26:25.011Z","2026-05-14T22:26:25.011Z"],["arbos-ft80038207","FT80038207","ARBOS","arbos","Nakrętka zabezpieczająca","Nakrętka zabezpieczająca","tractor",4.64,3.87,0,0,"EUR","green","package","Цена обновлена","https://bartsparts.com/products/arbos-ft80038207/","https://store-77uyis7lbs.mybigcommerce.com/content/images/brands/arbos.png","in_stock","2026-05-15T05:55:48.360Z","2026-05-15T05:55:48.360Z"],["arbos-ft80038218","FT80038218","ARBOS","arbos","Podkładka zabezpieczająca","Podkładka zabezpieczająca","tractor",9.98,8.32,0,0,"EUR","green","package","Цена обновлена","https://bartsparts.com/products/arbos-ft80038218/","https://store-77uyis7lbs.mybigcommerce.com/content/images/brands/arbos.png","in_stock","2026-05-15T05:55:48.360Z","2026-05-15T05:55:48.360Z"],["arbos-p5p37301127","P5P37301127","ARBOS","arbos","Nakrętka zabezpieczająca M40 x 1,5","Nakrętka zabezpieczająca M40 x 1,5","tractor",6.4,5.33,0,0,"EUR","green","package","Цена обновлена","https://bartsparts.com/products/arbos-p5p37301127/","https://store-77uyis7lbs.mybigcommerce.com/content/images/brands/arbos.png","in_stock","2026-05-15T05:55:48.360Z","2026-05-15T05:55:48.360Z"],["arbos-p5s52501025","P5S52501025","ARBOS","arbos","Zabezpieczenie plastikowe","Zabezpieczenie plastikowe","tractor",17.24,14.37,0,0,"EUR","green","package","Цена обновлена","https://bartsparts.com/products/arbos-p5s52501025/","https://store-77uyis7lbs.mybigcommerce.com/content/images/brands/arbos.png","in_stock","2026-05-15T05:55:48.360Z","2026-05-15T05:55:48.360Z"],["arbos-td904311k15103","TD904311K15103","ARBOS","arbos","Pierścień zabezpieczjący zwolnicy","Pierścień zabezpieczjący zwolnicy","tractor",10.33,8.61,0,0,"EUR","green","package","Цена обновлена","https://bartsparts.com/products/arbos-td904311k15103/","https://store-77uyis7lbs.mybigcommerce.com/content/images/brands/arbos.png","in_stock","2026-05-15T05:55:48.360Z","2026-05-15T05:55:48.360Z"],["arbos-te2s412010014k","TE2S412010014K","ARBOS","arbos","Podkładka zabezpieczająca","Podkładka zabezpieczająca","tractor",16.88,14.07,0,0,"EUR","green","package","Цена обновлена","https://bartsparts.com/products/arbos-te2s412010014k/","https://store-77uyis7lbs.mybigcommerce.com/content/images/brands/arbos.png","in_stock","2026-05-15T05:55:48.360Z","2026-05-15T05:55:48.360Z"],["arbos-te2s412010040k","TE2S412010040K","ARBOS","arbos","Podkładka zabezpieczająca","Podkładka zabezpieczająca","tractor",22.14,18.45,0,0,"EUR","green","package","Цена обновлена","https://bartsparts.com/products/arbos-te2s412010040k/","https://store-77uyis7lbs.mybigcommerce.com/content/images/brands/arbos.png","in_stock","2026-05-15T05:55:48.360Z","2026-05-15T05:55:48.360Z"],["avr-zab205","ZAB205","AVR","avr","ONDERLEGPLAATJE 32MM VERZ.GAT AVR","ONDERLEGPLAATJE 32MM VERZ.GAT AVR","tractor",3,2.5,0,0,"EUR","red","package","Цена обновлена","https://bartsparts.com/products/avr-zab205/","https://store-77uyis7lbs.mybigcommerce.com/content/images/brands/avr.png","in_stock","2026-05-15T05:55:48.360Z","2026-05-15T05:55:48.360Z"],["avr-zab325","ZAB325","AVR","avr","RECHT PLAATJE Ø5 x 32","RECHT PLAATJE Ø5 x 32","tractor",3,2.5,0,0,"EUR","red","package","Цена обновлена","https://bartsparts.com/products/avr-zab325/","https://store-77uyis7lbs.mybigcommerce.com/content/images/brands/avr.png","in_stock","2026-05-15T05:55:48.360Z","2026-05-15T05:55:48.360Z"],["avr-zab326","ZAB326","AVR","avr","ONDERLEGPLAATJE 32 CENTER AVR","ONDERLEGPLAATJE 32 CENTER AVR","tractor",3,2.5,0,0,"EUR","red","package","Цена обновлена","https://bartsparts.com/products/avr-zab326/","https://store-77uyis7lbs.mybigcommerce.com/content/images/brands/avr.png","in_stock","2026-05-15T05:55:48.360Z","2026-05-15T05:55:48.360Z"],["accord-kverneland-6080ac496838","6080AC496838","Accord - Kverneland","accord-kverneland","Ząb spulchniacza śladów, długi pasuje do Accord","Ząb spulchniacza śladów, długi pasuje do Accord","tractor",178.82,149.02,0,0,"EUR","blue","package","Цена обновлена","https://bartsparts.com/products/accord-kverneland-6080ac496838/","https://store-77uyis7lbs.mybigcommerce.com/content/images/brands/accord-kverneland.png","in_stock","2026-05-15T05:55:48.360Z","2026-05-15T05:55:48.360Z"],["bednar-km060061","KM060061","BEDNAR","bednar","ZĄB KPL STROM KM060061","ZĄB KPL STROM KM060061","tractor",9.26,7.72,0,0,"EUR","green","package","Цена обновлена","https://bartsparts.com/products/bednar-km060061/","https://store-77uyis7lbs.mybigcommerce.com/content/images/brands/bednar.png","in_stock","2026-05-15T15:38:14.931Z","2026-05-15T15:38:14.931Z"],["bepco-1235116725","1235116725","BEPCO","bepco","Case ih Zabezpieczenie 5116725","Case ih Zabezpieczenie 5116725","tractor",3,2.5,0,0,"EUR","amber","package","Цена обновлена","https://bartsparts.com/products/bepco-1235116725/","https://store-77uyis7lbs.mybigcommerce.com/content/images/brands/bepco.png","in_stock","2026-05-15T15:38:14.931Z","2026-05-15T15:38:14.931Z"],["belarus-502401020","502401020","Belarus","belarus","MT-CIĄGNIKI MTZ-FARMER ZABIERAK 50-2401020","MT-CIĄGNIKI MTZ-FARMER ZABIERAK 50-2401020","tractor",3.5,2.92,0,0,"EUR","green","package","Цена обновлена","https://bartsparts.com/products/belarus-502401020/","https://store-77uyis7lbs.mybigcommerce.com/content/images/brands/belarus.png","in_stock","2026-05-16T04:10:43.049Z","2026-05-16T04:10:43.049Z"],["belarus-804202019","804202019","Belarus","belarus","Końcówka WOM 6-fr. na ząbki /org/","Końcówka WOM 6-fr. na ząbki /org/","tractor",36.82,30.68,0,0,"EUR","green","package","Цена обновлена","https://bartsparts.com/products/belarus-804202019/","https://store-77uyis7lbs.mybigcommerce.com/content/images/brands/belarus.png","in_stock","2026-05-16T04:10:43.049Z","2026-05-16T04:10:43.049Z"],["bobcat-5jm50","5JM50","Bobcat","bobcat","pierścień zabezpieczający","pierścień zabezpieczający","tractor",4.22,3.52,0,0,"EUR","red","package","Цена обновлена","https://bartsparts.com/products/bobcat-5jm50/","https://store-77uyis7lbs.mybigcommerce.com/content/images/brands/bobcat.png","in_stock","2026-05-16T05:18:24.078Z","2026-05-16T05:18:24.078Z"],["bobcat-6698412","6698412","Bobcat","bobcat","ząb m6698412","ząb m6698412","tractor",69,57.5,0,0,"EUR","red","package","Цена обновлена","https://bartsparts.com/products/bobcat-6698412/","https://store-77uyis7lbs.mybigcommerce.com/content/images/brands/bobcat.png","in_stock","2026-05-16T05:18:24.078Z","2026-05-16T05:18:24.078Z"],["bobcat-6915389","6915389","Bobcat","bobcat","Zabezpieczenie Bobcat 6915389","Zabezpieczenie Bobcat 6915389","tractor",3,2.5,0,0,"EUR","red","package","Цена обновлена","https://bartsparts.com/products/bobcat-6915389/","https://store-77uyis7lbs.mybigcommerce.com/content/images/brands/bobcat.png","in_stock","2026-05-16T05:18:24.078Z","2026-05-16T05:18:24.078Z"],["bobcat-697912","697912","Bobcat","bobcat","ząb szufli m69791.2","ząb szufli m69791.2","tractor",29.6,24.67,0,0,"EUR","red","package","Цена обновлена","https://bartsparts.com/products/bobcat-697912/","https://store-77uyis7lbs.mybigcommerce.com/content/images/brands/bobcat.png","in_stock","2026-05-16T05:18:24.078Z","2026-05-16T05:18:24.078Z"],["bobcat-7190424","7190424","Bobcat","bobcat","Zabezpieczenie","Zabezpieczenie","tractor",3.91,3.26,0,0,"EUR","red","package","Цена обновлена","https://bartsparts.com/products/bobcat-7190424/","https://store-77uyis7lbs.mybigcommerce.com/content/images/brands/bobcat.png","in_stock","2026-05-16T05:18:24.078Z","2026-05-16T05:18:24.078Z"],["bobcat-7273535","7273535","Bobcat","bobcat","Zabezpieczenie","Zabezpieczenie","tractor",32.81,27.34,0,0,"EUR","red","package","Цена обновлена","https://bartsparts.com/products/bobcat-7273535/","https://store-77uyis7lbs.mybigcommerce.com/content/images/brands/bobcat.png","in_stock","2026-05-16T05:18:24.078Z","2026-05-16T05:18:24.078Z"],["bobcat-7519798","7519798","Bobcat","bobcat","Zabezpieczenie BOBCAT 7519798","Zabezpieczenie BOBCAT 7519798","tractor",92.21,76.84,0,0,"EUR","red","package","Цена обновлена","https://bartsparts.com/products/bobcat-7519798/","https://store-77uyis7lbs.mybigcommerce.com/content/images/brands/bobcat.png","in_stock","2026-05-16T05:18:24.078Z","2026-05-16T05:18:24.078Z"],["briggs-and-stratton-590545","590545","Briggs & Stratton","briggs-and-stratton","Zabierak rozrusznika B&S","Zabierak rozrusznika B&S","tractor",9.48,7.9,0,0,"EUR","amber","package","Цена обновлена","https://bartsparts.com/products/briggs-and-stratton-590545/","https://store-77uyis7lbs.mybigcommerce.com/content/images/brands/briggs-and-stratton.png","in_stock","2026-05-16T06:42:28.776Z","2026-05-16T06:42:28.776Z"],["carraro-090002161","090002161","Carraro","carraro","pierścień zabezpieczający 7028505","pierścień zabezpieczający 7028505","tractor",3,2.5,0,0,"EUR","danger","package","Цена обновлена","https://bartsparts.com/products/carraro-090002161/","https://store-77uyis7lbs.mybigcommerce.com/content/images/brands/carraro.png","in_stock","2026-05-16T14:08:19.866Z","2026-05-16T14:08:19.866Z"],["carraro-148030","148030","Carraro","carraro","Pierścień zabezpieczający CARRARO 148030-CR","Pierścień zabezpieczający CARRARO 148030-CR","tractor",13.96,11.63,0,0,"EUR","danger","package","Цена обновлена","https://bartsparts.com/products/carraro-148030/","https://store-77uyis7lbs.mybigcommerce.com/content/images/brands/carraro.png","in_stock","2026-05-16T14:08:19.866Z","2026-05-16T14:08:19.866Z"],["carraro-car125344","CAR125344","Carraro","carraro","Pierścień zabezpieczjący - Non Original","Pierścień zabezpieczjący - Non Original","tractor",3,2.5,0,0,"EUR","danger","package","Цена обновлена","https://bartsparts.com/products/carraro-car125344/","https://store-77uyis7lbs.mybigcommerce.com/content/images/brands/carraro.png","in_stock","2026-05-16T15:24:50.763Z","2026-05-16T15:24:50.763Z"],["case-ih-17517087374","17517087374","Case IH","case-ih","CNH Zabezpieczenie 17087374","CNH Zabezpieczenie 17087374","tractor",3,2.5,0,0,"EUR","red","package","Цена обновлена","https://bartsparts.com/products/case-ih-17517087374/","https://store-77uyis7lbs.mybigcommerce.com/content/images/brands/case-ih.png","in_stock","2026-05-16T22:14:29.474Z","2026-05-16T22:14:29.474Z"],["case-ih-275699a1lf","275699A1LF","Case IH","case-ih","Ząb czerpaka","Ząb czerpaka","tractor",29.98,24.98,0,0,"EUR","red","package","Цена обновлена","https://bartsparts.com/products/case-ih-275699a1lf/","https://store-77uyis7lbs.mybigcommerce.com/content/images/brands/case-ih.png","in_stock","2026-05-17T00:18:19.571Z","2026-05-17T00:18:19.571Z"],["case-ih-294220a1lf","294220A1LF","Case IH","case-ih","Ząb czerpaka - zabezpieczenie","Ząb czerpaka - zabezpieczenie","tractor",15.47,12.89,0,0,"EUR","red","package","Цена обновлена","https://bartsparts.com/products/case-ih-294220a1lf/","https://store-77uyis7lbs.mybigcommerce.com/content/images/brands/case-ih.png","in_stock","2026-05-17T04:42:02.293Z","2026-05-17T04:42:02.293Z"],["case-ih-5182717cnh","5182717CNH","Case IH","case-ih","PIERSCIEN SPR ZABEZP","PIERSCIEN SPR ZABEZP","tractor",3,2.5,0,0,"EUR","red","package","Цена обновлена","https://bartsparts.com/products/case-ih-5182717cnh/","https://store-77uyis7lbs.mybigcommerce.com/content/images/brands/case-ih.png","in_stock","2026-05-17T16:25:06.996Z","2026-05-17T16:25:06.996Z"],["case-ih-552010cnh","552010CNH","Case IH","case-ih","PODKLADKA ZABEZP","PODKLADKA ZABEZP","tractor",20.21,16.84,0,0,"EUR","red","package","Цена обновлена","https://bartsparts.com/products/case-ih-552010cnh/","https://store-77uyis7lbs.mybigcommerce.com/content/images/brands/case-ih.png","in_stock","2026-05-17T16:25:06.996Z","2026-05-17T16:25:06.996Z"],["case-ih-56368182982424","56368182982424","Case IH","case-ih","CASE PODKLADKA ZABEZPIECZAJACA","CASE PODKLADKA ZABEZPIECZAJACA","tractor",3.32,2.77,0,0,"EUR","red","package","Цена обновлена","https://bartsparts.com/products/case-ih-56368182982424/","https://store-77uyis7lbs.mybigcommerce.com/content/images/brands/case-ih.png","in_stock","2026-05-17T16:25:06.996Z","2026-05-17T16:25:06.996Z"],["case-ih-60003190","60003190","Case IH","case-ih","CNH Optum 300 CVX Zabawka 415717597","CNH Optum 300 CVX Zabawka 415717597","tractor",31.04,25.87,0,0,"EUR","red","package","Цена обновлена","https://bartsparts.com/products/case-ih-60003190/","https://store-77uyis7lbs.mybigcommerce.com/content/images/brands/case-ih.png","in_stock","2026-05-17T17:27:29.757Z","2026-05-17T17:27:29.757Z"],["case-ih-72274032","72274032","Case IH","case-ih","CASE Ząb czerpaka","CASE Ząb czerpaka","tractor",39.96,33.3,0,0,"EUR","red","package","Цена обновлена","https://bartsparts.com/products/case-ih-72274032/","https://store-77uyis7lbs.mybigcommerce.com/content/images/brands/case-ih.png","in_stock","2026-05-17T18:25:28.049Z","2026-05-17T18:25:28.049Z"],["case-ih-73000185505v","73000185505V","Case IH","case-ih","Ząb brony aktywnej HOWARD LH 73000185505V","Ząb brony aktywnej HOWARD LH 73000185505V","tractor",30.36,25.3,0,0,"EUR","red","package","Цена обновлена","https://bartsparts.com/products/case-ih-73000185505v/","https://store-77uyis7lbs.mybigcommerce.com/content/images/brands/case-ih.png","in_stock","2026-05-17T18:25:28.049Z","2026-05-17T18:25:28.049Z"],["case-ih-87334403","87334403","Case IH","case-ih","87334403 OSŁONA ZABEZP.","87334403 OSŁONA ZABEZP.","tractor",38.28,31.9,0,0,"EUR","red","package","Цена обновлена","https://bartsparts.com/products/case-ih-87334403/","https://store-77uyis7lbs.mybigcommerce.com/content/images/brands/case-ih.png","in_stock","2026-05-18T06:19:06.432Z","2026-05-18T06:19:06.432Z"],["case-ih-87347229","87347229","Case IH","case-ih","87347229 NASADKA ZABEZP.","87347229 NASADKA ZABEZP.","tractor",31.93,26.61,0,0,"EUR","red","package","Цена обновлена","https://bartsparts.com/products/case-ih-87347229/","https://store-77uyis7lbs.mybigcommerce.com/content/images/brands/case-ih.png","in_stock","2026-05-18T06:19:06.432Z","2026-05-18T06:19:06.432Z"],["case-ih-no-87347166","87347166","Case IH NO","case-ih-no","PIERŚCIEŃ ZABEZPIECZAJĄCY WOM 87347166-Non Original","PIERŚCIEŃ ZABEZPIECZAJĄCY WOM 87347166-Non Original","tractor",17,14.17,0,0,"EUR","amber","package","Цена обновлена","https://bartsparts.com/products/case-ih-no-87347166/","https://store-77uyis7lbs.mybigcommerce.com/content/images/brands/case-ih-no.png","in_stock","2026-05-19T06:11:30.359Z","2026-05-19T06:11:30.359Z"],["claas-0000262590","0000262590","Claas","claas","ZABEZPIECZENIE","ZABEZPIECZENIE","tractor",0,0,0,0,"EUR","green","package","Нет в наличии","https://bartsparts.com/products/claas-0000262590/","https://cdn11.bigcommerce.com/s-77uyis7lbs/stencil/64efad60-30c7-013f-ff90-5accf53efe44/e/f341cdf0-302d-013f-3d40-0adaba195be6/img/merken/no_logo.png","out_of_stock","2026-05-19T06:11:30.359Z","2026-05-19T06:11:30.359Z"],["claas-0001394160","0001394160","Claas","claas","0001394160 / CLAAS PIASTA ZABIERAKA-0001394160","0001394160 / CLAAS PIASTA ZABIERAKA-0001394160","tractor",287.84,239.87,0,0,"EUR","green","package","Цена обновлена","https://bartsparts.com/products/claas-0001394160/","https://store-77uyis7lbs.mybigcommerce.com/content/images/brands/claas.png","in_stock","2026-05-19T06:11:30.359Z","2026-05-19T06:11:30.359Z"],["claas-0001816292","0001816292","Claas","claas","ZABEZPIECZENIE","ZABEZPIECZENIE","tractor",0,0,0,0,"EUR","green","package","Нет в наличии","https://bartsparts.com/products/claas-0001816292/","https://cdn11.bigcommerce.com/s-77uyis7lbs/stencil/64efad60-30c7-013f-ff90-5accf53efe44/e/f341cdf0-302d-013f-3d40-0adaba195be6/img/merken/no_logo.png","out_of_stock","2026-05-19T06:11:30.359Z","2026-05-19T06:11:30.359Z"],["claas-0003193630","0003193630","Claas","claas","Sworzeń siłownika zabieraka","Sworzeń siłownika zabieraka","tractor",137.16,114.3,0,0,"EUR","green","package","Цена обновлена","https://bartsparts.com/products/claas-0003193630/","https://store-77uyis7lbs.mybigcommerce.com/content/images/brands/claas.png","in_stock","2026-05-19T16:44:00.934Z","2026-05-19T16:44:00.934Z"],["claas-0003194440","0003194440","Claas","claas","Sworzeń siłownika zabieraka","Sworzeń siłownika zabieraka","tractor",58.14,48.45,0,0,"EUR","green","package","Цена обновлена","https://bartsparts.com/products/claas-0003194440/","https://store-77uyis7lbs.mybigcommerce.com/content/images/brands/claas.png","in_stock","2026-05-19T16:44:00.934Z","2026-05-19T16:44:00.934Z"],["claas-0003230990","0003230990","Claas","claas","Ząb łyżki","Ząb łyżki","tractor",23.59,19.66,0,0,"EUR","green","package","Цена обновлена","https://bartsparts.com/products/claas-0003230990/","https://store-77uyis7lbs.mybigcommerce.com/content/images/brands/claas.png","in_stock","2026-05-19T16:44:00.934Z","2026-05-19T16:44:00.934Z"],["claas-0007759330","0007759330","Claas","claas","0007759330 / CLAAS ZABEZPIECZENIE 0007759330","0007759330 / CLAAS ZABEZPIECZENIE 0007759330","tractor",518.33,431.94,0,0,"EUR","green","package","Цена обновлена","https://bartsparts.com/products/claas-0007759330/","https://store-77uyis7lbs.mybigcommerce.com/content/images/brands/claas.png","in_stock","2026-05-20T06:13:04.867Z","2026-05-20T06:13:04.867Z"],["claas-0009828020","0009828020","Claas","claas","Zabezpieczenie obudowy bębna","Zabezpieczenie obudowy bębna","tractor",12.18,10.15,0,0,"EUR","green","package","Цена обновлена","https://bartsparts.com/products/claas-0009828020/","https://store-77uyis7lbs.mybigcommerce.com/content/images/brands/claas.png","in_stock","2026-05-20T06:13:04.867Z","2026-05-20T06:13:04.867Z"],["john-deere-56m5258org","56M5258ORG","John Deere","john-deere","Zabezpieczenie /org.JD/","Zabezpieczenie /org.JD/","tractor",3,2.5,0,0,"EUR","green","package","Цена обновлена","https://bartsparts.com/products/john-deere-56m5258org/","https://store-77uyis7lbs.mybigcommerce.com/content/images/brands/john-deere.png","in_stock","2026-05-14T16:29:00.778Z","2026-05-14T16:29:00.778Z"],["manitou-zab810","ZAB810","Manitou","manitou","Manitou ZAB810","ZAB810","tractor",0,0,0,0,"EUR","amber","package","Цена по запросу","https://bartsparts.com/products/manitou-zab810/","","","",""],["nsk-zab880cg120","ZAB880CG120","NSK","nsk","NSK ZAB880CG120","ZAB880CG120","tractor",0,0,0,0,"EUR","green","package","Цена по запросу","https://bartsparts.com/products/nsk-zab880cg120/","","","",""],["unbranded-zabawka3123323","ZABAWKA3123323","Unbranded","unbranded","Unbranded ZABAWKA3123323","ZABAWKA3123323","tractor",0,0,0,0,"EUR","amber","package","Цена по запросу","https://bartsparts.com/products/unbranded-zabawka3123323/","","","",""],["unbranded-zabawka3125475","ZABAWKA3125475","Unbranded","unbranded","Unbranded ZABAWKA3125475","ZABAWKA3125475","tractor",0,0,0,0,"EUR","amber","package","Цена по запросу","https://bartsparts.com/products/unbranded-zabawka3125475/","","","",""],["unbranded-zabawka3128300","ZABAWKA3128300","Unbranded","unbranded","Unbranded ZABAWKA3128300","ZABAWKA3128300","tractor",0,0,0,0,"EUR","amber","package","Цена по запросу","https://bartsparts.com/products/unbranded-zabawka3128300/","","","",""],["unbranded-zabawka3130285","ZABAWKA3130285","Unbranded","unbranded","Unbranded ZABAWKA3130285","ZABAWKA3130285","tractor",0,0,0,0,"EUR","amber","package","Цена по запросу","https://bartsparts.com/products/unbranded-zabawka3130285/","","","",""],["unbranded-zabawka3142341","ZABAWKA3142341","Unbranded","unbranded","Unbranded ZABAWKA3142341","ZABAWKA3142341","tractor",0,0,0,0,"EUR","amber","package","Цена по запросу","https://bartsparts.com/products/unbranded-zabawka3142341/","","","",""],["unbranded-zabawka3157118","ZABAWKA3157118","Unbranded","unbranded","Unbranded ZABAWKA3157118","ZABAWKA3157118","tractor",0,0,0,0,"EUR","amber","package","Цена по запросу","https://bartsparts.com/products/unbranded-zabawka3157118/","","","",""],["unbranded-zabawka3167726","ZABAWKA3167726","Unbranded","unbranded","Unbranded ZABAWKA3167726","ZABAWKA3167726","tractor",0,0,0,0,"EUR","amber","package","Цена по запросу","https://bartsparts.com/products/unbranded-zabawka3167726/","","","",""],["unbranded-zabawka3167727","ZABAWKA3167727","Unbranded","unbranded","Unbranded ZABAWKA3167727","ZABAWKA3167727","tractor",0,0,0,0,"EUR","amber","package","Цена по запросу","https://bartsparts.com/products/unbranded-zabawka3167727/","","","",""],["unbranded-zabawka3177626","ZABAWKA3177626","Unbranded","unbranded","Unbranded ZABAWKA3177626","ZABAWKA3177626","tractor",0,0,0,0,"EUR","amber","package","Цена по запросу","https://bartsparts.com/products/unbranded-zabawka3177626/","","","",""],["unbranded-zabezpieczeniaspr-yste","ZABEZPIECZENIASPRĘŻYSTE","Unbranded","unbranded","Unbranded ZABEZPIECZENIASPRĘŻYSTE","ZABEZPIECZENIASPRĘŻYSTE","tractor",0,0,0,0,"EUR","amber","package","Цена по запросу","https://bartsparts.com/products/unbranded-zabezpieczeniaspr%C4%99%C5%BCyste/","","","",""],["unbranded-z-b-adowacza680","ZĄBŁADOWACZA680","Unbranded","unbranded","Unbranded ZĄBŁADOWACZA680","ZĄBŁADOWACZA680","tractor",0,0,0,0,"EUR","amber","package","Цена по запросу","https://bartsparts.com/products/unbranded-z%C4%85b%C5%82adowacza680/","","","",""]]}
